text2sparql_client/__init__.py
text2sparql_client/cli.py
text2sparql_client/commands/__init__.py
text2sparql_client/commands/ask.py
text2sparql_client/commands/evaluate.py
text2sparql_client/commands/serve.py
text2sparql_client/context.py
text2sparql_client/database.py
text2sparql_client/models/__init__.py
text2sparql_client/models/questions_file.py
text2sparql_client/models/response.py
text2sparql_client/request.py
text2sparql_client/utils/__init__.py
text2sparql_client/utils/evaluation_metrics.py
text2sparql_client/utils/query_rdf.py
text2sparql_client-1.4.2.dist-info/LICENSE
text2sparql_client-1.4.2.dist-info/METADATA
text2sparql_client-1.4.2.dist-info/WHEEL
text2sparql_client-1.4.2.dist-info/entry_points.txt
text2sparql_client-1.4.2.dist-info/RECORD
