Metadata-Version: 2.3
Name: text2sparql-client
Version: 1.4.2
Summary: Command Line Client to retrieve SPARQL results from a TEXT2SPARQL conform endpoint.
License: Apache-2.0
Author: Sebastian Tramp
Author-email: sebastian.tramp@eccenca.com
Requires-Python: >=3.11,<4
Classifier: Development Status :: 4 - Beta
Classifier: License :: OSI Approved :: Apache Software License
Classifier: Programming Language :: Python :: 3
Classifier: Programming Language :: Python :: 3.11
Classifier: Programming Language :: Python :: 3.12
Classifier: Programming Language :: Python :: 3.13
Requires-Dist: SPARQLWrapper (>=2.0.0,<3.0.0)
Requires-Dist: click (>=8.1.8,<9.0.0)
Requires-Dist: fastapi (>=0.115.12,<0.116.0)
Requires-Dist: loguru (>=0.7.3,<0.8.0)
Requires-Dist: numpy (>=1.15.1,<2.0.0)
Requires-Dist: pydantic-settings (>=2.8.1,<3.0.0)
Requires-Dist: pytrec-eval (>=0.5,<0.6)
Requires-Dist: pyyaml (>=6.0.2,<7.0.0)
Requires-Dist: requests (>=2.32.3,<3.0.0)
Requires-Dist: scipy (>=1.1.0,<2.0.0)
Requires-Dist: tqdm (>=4.67.1,<5.0.0)
Requires-Dist: uvicorn (>=0.34.1,<0.35.0)
Project-URL: Homepage, https://github.com/aksw/text2sparql-client
